adafruit_max9744.py
adafruit_circuitpython_max9744-1.2.22.dist-info/licenses/LICENSE
adafruit_circuitpython_max9744-1.2.22.dist-info/METADATA
adafruit_circuitpython_max9744-1.2.22.dist-info/WHEEL
adafruit_circuitpython_max9744-1.2.22.dist-info/top_level.txt
adafruit_circuitpython_max9744-1.2.22.dist-info/RECORD
